river/__init__.py
river/cli/__init__.py
river/cli/__main__.py
river/cli/commands/__init__.py
river/cli/commands/compute_section.py
river/cli/commands/coordinate_transform.py
river/cli/commands/define_roi_masks.py
river/cli/commands/exceptions.py
river/cli/commands/piv_pipeline.py
river/cli/commands/utils.py
river/cli/commands/video_to_frames.py
river/core/__init__.py
river/core/compute_section.py
river/core/coordinate_transform.py
river/core/define_roi_masks.py
river/core/exceptions.py
river/core/image_preprocessing.py
river/core/piv_fftmulti.py
river/core/piv_loop.py
river/core/piv_pipeline.py
river/core/video_to_frames.py
river_cli-3.2.0.dist-info/licenses/LICENSE
river_cli-3.2.0.dist-info/METADATA
river_cli-3.2.0.dist-info/WHEEL
river_cli-3.2.0.dist-info/entry_points.txt
river_cli-3.2.0.dist-info/top_level.txt
river_cli-3.2.0.dist-info/RECORD
