Metadata-Version: 2.4
Name: river-cli
Version: 3.2.0
Summary: A CLI application for Large Scale Particle Image Velocimetry (LSPIV).
Author-email: Antoine Patalano <antoine.patalano@unc.edu.ar>, Nicolas Stefani <nicolas471@gmail.com>, Tomas Stefani <tomyste02@gmail.com>
License-Expression: AGPL-3.0-or-later
Project-URL: Homepage, https://github.com/aPatal/RIVeR/
Keywords: cli,lspiv,flow,discharge,velocity,analysis,hydraulic,models
Classifier: Programming Language :: Python
Classifier: Programming Language :: Python :: 3
Classifier: Programming Language :: Python :: 3.12
Requires-Python: >=3.11
License-File: LICENSE
Requires-Dist: click>=8.1.3
Requires-Dist: opencv-python-headless==4.10.0.84
Requires-Dist: matplotlib>=3.9.0
Requires-Dist: scipy<1.14
Requires-Dist: tqdm>=4.67.0
Requires-Dist: numba==0.60.0
Requires-Dist: tablib[ods,xls,xlsx]==3.8.0
Requires-Dist: pyfftw==0.15.0
Provides-Extra: dev
Requires-Dist: ruff; extra == "dev"
Requires-Dist: bumpver; extra == "dev"
Dynamic: license-file
